cinetext.py
cinetext-0.3.0.dist-info/METADATA
cinetext-0.3.0.dist-info/WHEEL
cinetext-0.3.0.dist-info/top_level.txt
cinetext-0.3.0.dist-info/RECORD
