Metadata-Version: 2.4
Name: cinetext
Version: 0.3.0
Summary: A Python library for cinematic text effects in command-line interfaces.
Home-page: https://github.com/username/cinetext
Author: Anay Rustogi
Author-email: codemaster.ar@gmail.com
Classifier: Programming Language :: Python :: 3
Classifier: License :: OSI Approved :: MIT License
Classifier: Operating System :: OS Independent
Classifier: Topic :: Terminals
Requires-Python: >=3.6
Dynamic: author
Dynamic: author-email
Dynamic: classifier
Dynamic: description
Dynamic: description-content-type
Dynamic: home-page
Dynamic: requires-python
Dynamic: summary
